tf2_utilities-3.1.0.dist-info/licenses/LICENSE
tf2utilities/__init__.py
tf2utilities/main.py
tf2utilities/schema.py
tf2utilities/sku.py
tf2utilities/webapi.py
tf2_utilities-3.1.0.dist-info/METADATA
tf2_utilities-3.1.0.dist-info/WHEEL
tf2_utilities-3.1.0.dist-info/top_level.txt
tf2_utilities-3.1.0.dist-info/RECORD
