Metadata-Version: 2.4
Name: tf2-utilities
Version: 3.1.0
Summary: Get information about TF2 items, effects, skins and more
Home-page: https://github.com/j0hnnyblack/python-tf2-utilities
Author: Johnny Black
Author-email: lokedixon@hotmail.my
License: MIT
Keywords: tf2,teamfortress2,steam,trade,trading
Classifier: License :: OSI Approved :: MIT License
Classifier: Programming Language :: Python
Classifier: Programming Language :: Python :: 3.9
Classifier: Programming Language :: Python :: 3.10
Classifier: Programming Language :: Python :: 3.11
License-File: LICENSE
Requires-Dist: requests
Requires-Dist: vdf
Dynamic: author
Dynamic: author-email
Dynamic: classifier
Dynamic: description
Dynamic: description-content-type
Dynamic: home-page
Dynamic: keywords
Dynamic: license
Dynamic: license-file
Dynamic: requires-dist
Dynamic: summary
